{
  "category": "API",
  "alternative": [{
    "id": 11,
    "updateTime": "2020-02-26 15:51:53",
    "sourceId": 2,
    "title": "news",
    "path": "/new",
    "method": null,
    "prefix": null,
    "value": "{\"definitions\":{},\"$schema\":\"http://json-schema.org/draft-07/schema#\",\"$id\":\"http://example.com/root.json\",\"type\":\"object\",\"title\":\"The Root Schema\",\"required\":[\"title\",\"subTitle\",\"cover\",\"classifyId\",\"classifyTitle\",\"isUrl\",\"url\",\"content\",\"authorId\",\"authorName\",\"needCheck\"],\"properties\":{\"title\":{\"$id\":\"#/properties/title\",\"type\":\"string\",\"title\":\"The Title Schema\",\"default\":\"\",\"examples\":[\"标题\"],\"pattern\":\"^(.*)$\"},\"subTitle\":{\"$id\":\"#/properties/subTitle\",\"type\":\"string\",\"title\":\"The Subtitle Schema\",\"default\":\"\",\"examples\":[\"副标题\"],\"pattern\":\"^(.*)$\"},\"cover\":{\"$id\":\"#/properties/cover\",\"type\":\"string\",\"title\":\"The Cover Schema\",\"default\":\"\",\"examples\":[\"image url\"],\"pattern\":\"^(.*)$\"},\"classifyId\":{\"$id\":\"#/properties/classifyId\",\"type\":\"integer\",\"title\":\"The Classifyid Schema\",\"default\":0,\"examples\":[1]},\"classifyTitle\":{\"$id\":\"#/properties/classifyTitle\",\"type\":\"string\",\"title\":\"The Classifytitle Schema\",\"default\":\"\",\"examples\":[\"分类标题\"],\"pattern\":\"^(.*)$\"},\"isUrl\":{\"$id\":\"#/properties/isUrl\",\"type\":\"boolean\",\"title\":\"The Isurl Schema\",\"default\":false,\"examples\":[true]},\"url\":{\"$id\":\"#/properties/url\",\"type\":\"string\",\"title\":\"The Url Schema\",\"default\":\"\",\"examples\":[\"new url\"],\"pattern\":\"^(.*)$\"},\"content\":{\"$id\":\"#/properties/content\",\"type\":\"string\",\"title\":\"The Content Schema\",\"default\":\"\",\"examples\":[\"内容\"],\"pattern\":\"^(.*)$\"},\"authorId\":{\"$id\":\"#/properties/authorId\",\"type\":\"string\",\"title\":\"The Authorid Schema\",\"default\":\"\",\"examples\":[\"作者ID\"],\"pattern\":\"^(.*)$\"},\"authorName\":{\"$id\":\"#/properties/authorName\",\"type\":\"string\",\"title\":\"The Authorname Schema\",\"default\":\"\",\"examples\":[\"作者名字\"],\"pattern\":\"^(.*)$\"},\"needCheck\":{\"$id\":\"#/properties/needCheck\",\"type\":\"integer\",\"title\":\"The Needcheck Schema\",\"default\":0,\"examples\":[1]}}}",
    "smColumns": [{
      "id": 96,
      "updateTime": "2020-02-26 15:51:53",
      "sourceId": 2,
      "resourceId": 11,
      "columnId": null,
      "title": "cover",
      "column": "cover",
      "type": "string",
      "arrayType": null,
      "pathTitle": "news@cover",
      "path": "$.cover",
      "index": 0,
      "checked": 1
    }, {
      "id": 97,
      "updateTime": "2020-02-26 15:51:53",
      "sourceId": 2,
      "resourceId": 11,
      "columnId": null,
      "title": "subTitle",
      "column": "subTitle",
      "type": "string",
      "arrayType": null,
      "pathTitle": "news@subTitle",
      "path": "$.subTitle",
      "index": 0,
      "checked": 1
    }, {
      "id": 98,
      "updateTime": "2020-02-26 15:51:53",
      "sourceId": 2,
      "resourceId": 11,
      "columnId": null,
      "title": "classifyId",
      "column": "classifyId",
      "type": "integer",
      "arrayType": null,
      "pathTitle": "news@classifyId",
      "path": "$.classifyId",
      "index": 0,
      "checked": 1
    }, {
      "id": 99,
      "updateTime": "2020-02-26 15:51:53",
      "sourceId": 2,
      "resourceId": 11,
      "columnId": null,
      "title": "authorName",
      "column": "authorName",
      "type": "string",
      "arrayType": null,
      "pathTitle": "news@authorName",
      "path": "$.authorName",
      "index": 0,
      "checked": 1
    }, {
      "id": 100,
      "updateTime": "2020-02-26 15:51:53",
      "sourceId": 2,
      "resourceId": 11,
      "columnId": null,
      "title": "classifyTitle",
      "column": "classifyTitle",
      "type": "string",
      "arrayType": null,
      "pathTitle": "news@classifyTitle",
      "path": "$.classifyTitle",
      "index": 0,
      "checked": 1
    }, {
      "id": 101,
      "updateTime": "2020-02-26 15:51:53",
      "sourceId": 2,
      "resourceId": 11,
      "columnId": null,
      "title": "isUrl",
      "column": "isUrl",
      "type": "boolean",
      "arrayType": null,
      "pathTitle": "news@isUrl",
      "path": "$.isUrl",
      "index": 0,
      "checked": 1
    }, {
      "id": 102,
      "updateTime": "2020-02-26 15:51:53",
      "sourceId": 2,
      "resourceId": 11,
      "columnId": null,
      "title": "needCheck",
      "column": "needCheck",
      "type": "integer",
      "arrayType": null,
      "pathTitle": "news@needCheck",
      "path": "$.needCheck",
      "index": 0,
      "checked": 1
    }, {
      "id": 103,
      "updateTime": "2020-02-26 15:51:53",
      "sourceId": 2,
      "resourceId": 11,
      "columnId": null,
      "title": "title",
      "column": "title",
      "type": "string",
      "arrayType": null,
      "pathTitle": "news@title",
      "path": "$.title",
      "index": 0,
      "checked": 1
    }, {
      "id": 104,
      "updateTime": "2020-02-26 15:51:53",
      "sourceId": 2,
      "resourceId": 11,
      "columnId": null,
      "title": "authorId",
      "column": "authorId",
      "type": "string",
      "arrayType": null,
      "pathTitle": "news@authorId",
      "path": "$.authorId",
      "index": 0,
      "checked": 1
    }, {
      "id": 105,
      "updateTime": "2020-02-26 15:51:53",
      "sourceId": 2,
      "resourceId": 11,
      "columnId": null,
      "title": "url",
      "column": "url",
      "type": "string",
      "arrayType": null,
      "pathTitle": "news@url",
      "path": "$.url",
      "index": 0,
      "checked": 1
    }, {
      "id": 106,
      "updateTime": "2020-02-26 15:51:53",
      "sourceId": 2,
      "resourceId": 11,
      "columnId": null,
      "title": "content",
      "column": "content",
      "type": "string",
      "arrayType": null,
      "pathTitle": "news@content",
      "path": "$.content",
      "index": 0,
      "checked": 1
    }],
    "checkColumns": [{
      "id": 96,
      "updateTime": "2020-02-26 15:51:53",
      "sourceId": 2,
      "resourceId": 11,
      "columnId": null,
      "title": "cover",
      "column": "cover",
      "type": "string",
      "arrayType": null,
      "pathTitle": "news@cover",
      "path": "$.cover",
      "index": 0,
      "checked": 1
    }, {
      "id": 97,
      "updateTime": "2020-02-26 15:51:53",
      "sourceId": 2,
      "resourceId": 11,
      "columnId": null,
      "title": "subTitle",
      "column": "subTitle",
      "type": "string",
      "arrayType": null,
      "pathTitle": "news@subTitle",
      "path": "$.subTitle",
      "index": 0,
      "checked": 1
    }, {
      "id": 98,
      "updateTime": "2020-02-26 15:51:53",
      "sourceId": 2,
      "resourceId": 11,
      "columnId": null,
      "title": "classifyId",
      "column": "classifyId",
      "type": "integer",
      "arrayType": null,
      "pathTitle": "news@classifyId",
      "path": "$.classifyId",
      "index": 0,
      "checked": 1
    }, {
      "id": 99,
      "updateTime": "2020-02-26 15:51:53",
      "sourceId": 2,
      "resourceId": 11,
      "columnId": null,
      "title": "authorName",
      "column": "authorName",
      "type": "string",
      "arrayType": null,
      "pathTitle": "news@authorName",
      "path": "$.authorName",
      "index": 0,
      "checked": 1
    }, {
      "id": 100,
      "updateTime": "2020-02-26 15:51:53",
      "sourceId": 2,
      "resourceId": 11,
      "columnId": null,
      "title": "classifyTitle",
      "column": "classifyTitle",
      "type": "string",
      "arrayType": null,
      "pathTitle": "news@classifyTitle",
      "path": "$.classifyTitle",
      "index": 0,
      "checked": 1
    }, {
      "id": 101,
      "updateTime": "2020-02-26 15:51:53",
      "sourceId": 2,
      "resourceId": 11,
      "columnId": null,
      "title": "isUrl",
      "column": "isUrl",
      "type": "boolean",
      "arrayType": null,
      "pathTitle": "news@isUrl",
      "path": "$.isUrl",
      "index": 0,
      "checked": 1
    }, {
      "id": 102,
      "updateTime": "2020-02-26 15:51:53",
      "sourceId": 2,
      "resourceId": 11,
      "columnId": null,
      "title": "needCheck",
      "column": "needCheck",
      "type": "integer",
      "arrayType": null,
      "pathTitle": "news@needCheck",
      "path": "$.needCheck",
      "index": 0,
      "checked": 1
    }, {
      "id": 103,
      "updateTime": "2020-02-26 15:51:53",
      "sourceId": 2,
      "resourceId": 11,
      "columnId": null,
      "title": "title",
      "column": "title",
      "type": "string",
      "arrayType": null,
      "pathTitle": "news@title",
      "path": "$.title",
      "index": 0,
      "checked": 1
    }, {
      "id": 104,
      "updateTime": "2020-02-26 15:51:53",
      "sourceId": 2,
      "resourceId": 11,
      "columnId": null,
      "title": "authorId",
      "column": "authorId",
      "type": "string",
      "arrayType": null,
      "pathTitle": "news@authorId",
      "path": "$.authorId",
      "index": 0,
      "checked": 1
    }, {
      "id": 105,
      "updateTime": "2020-02-26 15:51:53",
      "sourceId": 2,
      "resourceId": 11,
      "columnId": null,
      "title": "url",
      "column": "url",
      "type": "string",
      "arrayType": null,
      "pathTitle": "news@url",
      "path": "$.url",
      "index": 0,
      "checked": 1
    }, {
      "id": 106,
      "updateTime": "2020-02-26 15:51:53",
      "sourceId": 2,
      "resourceId": 11,
      "columnId": null,
      "title": "content",
      "column": "content",
      "type": "string",
      "arrayType": null,
      "pathTitle": "news@content",
      "path": "$.content",
      "index": 0,
      "checked": 1
    }]
  }, {
    "id": 12,
    "updateTime": "2020-02-26 15:51:53",
    "sourceId": 2,
    "title": "test",
    "path": "/test",
    "method": null,
    "prefix": null,
    "value": "{\"definitions\":{},\"$schema\":\"http://json-schema.org/draft-07/schema#\",\"$id\":\"http://example.com/root.json\",\"type\":\"object\",\"title\":\"The Root Schema\",\"required\":[\"checked\",\"dimensions\",\"id\",\"name\",\"price\",\"tags\"],\"properties\":{\"checked\":{\"$id\":\"#/properties/checked\",\"type\":\"boolean\",\"title\":\"The Checked Schema\",\"default\":false,\"examples\":[false]},\"dimensions\":{\"$id\":\"#/properties/dimensions\",\"type\":\"object\",\"title\":\"The Dimensions Schema\",\"required\":[\"width\",\"height\"],\"properties\":{\"width\":{\"$id\":\"#/properties/dimensions/properties/width\",\"type\":\"integer\",\"title\":\"The Width Schema\",\"default\":0,\"examples\":[5]},\"height\":{\"$id\":\"#/properties/dimensions/properties/height\",\"type\":\"integer\",\"title\":\"The Height Schema\",\"default\":0,\"examples\":[10]}}},\"id\":{\"$id\":\"#/properties/id\",\"type\":\"integer\",\"title\":\"The Id Schema\",\"default\":0,\"examples\":[1]},\"name\":{\"$id\":\"#/properties/name\",\"type\":\"string\",\"title\":\"The Name Schema\",\"default\":\"\",\"examples\":[\"A green door\"],\"pattern\":\"^(.*)$\"},\"price\":{\"$id\":\"#/properties/price\",\"type\":\"number\",\"title\":\"The Price Schema\",\"default\":0.0,\"examples\":[12.5]},\"tags\":{\"$id\":\"#/properties/tags\",\"type\":\"array\",\"title\":\"The Tags Schema\",\"items\":{\"$id\":\"#/properties/tags/items\",\"type\":\"object\",\"title\":\"The Items Schema\",\"required\":[\"id\",\"name\"],\"properties\":{\"id\":{\"$id\":\"#/properties/tags/items/properties/id\",\"type\":\"integer\",\"title\":\"The Id Schema\",\"default\":0,\"examples\":[1]},\"name\":{\"$id\":\"#/properties/tags/items/properties/name\",\"type\":\"string\",\"title\":\"The Name Schema\",\"default\":\"\",\"examples\":[\"home\"],\"pattern\":\"^(.*)$\"}}}}}}",
    "smColumns": [{
      "id": 107,
      "updateTime": "2020-02-26 15:51:53",
      "sourceId": 2,
      "resourceId": 12,
      "columnId": null,
      "title": "price",
      "column": "price",
      "type": "number",
      "arrayType": null,
      "pathTitle": "test@price",
      "path": "$.price",
      "index": 0,
      "checked": 1
    }, {
      "id": 108,
      "updateTime": "2020-02-26 15:51:53",
      "sourceId": 2,
      "resourceId": 12,
      "columnId": null,
      "title": "name",
      "column": "name",
      "type": "string",
      "arrayType": null,
      "pathTitle": "test@name",
      "path": "$.name",
      "index": 0,
      "checked": 1
    }, {
      "id": 109,
      "updateTime": "2020-02-26 15:51:53",
      "sourceId": 2,
      "resourceId": 12,
      "columnId": null,
      "title": "checked",
      "column": "checked",
      "type": "boolean",
      "arrayType": null,
      "pathTitle": "test@checked",
      "path": "$.checked",
      "index": 0,
      "checked": 1
    }, {
      "id": 110,
      "updateTime": "2020-02-26 15:51:53",
      "sourceId": 2,
      "resourceId": 12,
      "columnId": null,
      "title": "id",
      "column": "id",
      "type": "integer",
      "arrayType": null,
      "pathTitle": "test@id",
      "path": "$.id",
      "index": 0,
      "checked": 1
    }, {
      "id": 111,
      "updateTime": "2020-02-26 15:51:53",
      "sourceId": 2,
      "resourceId": 12,
      "columnId": null,
      "title": "width",
      "column": "width",
      "type": "integer",
      "arrayType": null,
      "pathTitle": "test@The Dimensions Schema@width",
      "path": "$.dimensions.width",
      "index": 0,
      "checked": 1
    }, {
      "id": 112,
      "updateTime": "2020-02-26 15:51:53",
      "sourceId": 2,
      "resourceId": 12,
      "columnId": null,
      "title": "height",
      "column": "height",
      "type": "integer",
      "arrayType": null,
      "pathTitle": "test@The Dimensions Schema@height",
      "path": "$.dimensions.height",
      "index": 0,
      "checked": 1
    }, {
      "id": 113,
      "updateTime": "2020-02-26 15:51:53",
      "sourceId": 2,
      "resourceId": 12,
      "columnId": null,
      "title": "dimensions",
      "column": null,
      "type": "object",
      "arrayType": null,
      "pathTitle": "test@The Dimensions Schema",
      "path": "$.dimensions",
      "index": 1,
      "checked": 1
    }, {
      "id": 114,
      "updateTime": "2020-02-26 15:51:53",
      "sourceId": 2,
      "resourceId": 12,
      "columnId": null,
      "title": "tags",
      "column": null,
      "type": "array",
      "arrayType": "object",
      "pathTitle": "test@The Tags Schema",
      "path": "$.tags[*]",
      "index": 1,
      "checked": 1
    }, {
      "id": 115,
      "updateTime": "2020-02-26 15:51:53",
      "sourceId": 2,
      "resourceId": 12,
      "columnId": null,
      "title": "name",
      "column": "name",
      "type": "string",
      "arrayType": null,
      "pathTitle": "test@The Tags Schema@name",
      "path": "$.tags[*].name",
      "index": 1,
      "checked": 1
    }, {
      "id": 116,
      "updateTime": "2020-02-26 15:51:53",
      "sourceId": 2,
      "resourceId": 12,
      "columnId": null,
      "title": "id",
      "column": "id",
      "type": "integer",
      "arrayType": null,
      "pathTitle": "test@The Tags Schema@id",
      "path": "$.tags[*].id",
      "index": 1,
      "checked": 1
    }],
    "checkColumns": [{
      "id": 107,
      "updateTime": "2020-02-26 15:51:53",
      "sourceId": 2,
      "resourceId": 12,
      "columnId": null,
      "title": "price",
      "column": "price",
      "type": "number",
      "arrayType": null,
      "pathTitle": "test@price",
      "path": "$.price",
      "index": 0,
      "checked": 1
    }, {
      "id": 108,
      "updateTime": "2020-02-26 15:51:53",
      "sourceId": 2,
      "resourceId": 12,
      "columnId": null,
      "title": "name",
      "column": "name",
      "type": "string",
      "arrayType": null,
      "pathTitle": "test@name",
      "path": "$.name",
      "index": 0,
      "checked": 1
    }, {
      "id": 109,
      "updateTime": "2020-02-26 15:51:53",
      "sourceId": 2,
      "resourceId": 12,
      "columnId": null,
      "title": "checked",
      "column": "checked",
      "type": "boolean",
      "arrayType": null,
      "pathTitle": "test@checked",
      "path": "$.checked",
      "index": 0,
      "checked": 1
    }, {
      "id": 110,
      "updateTime": "2020-02-26 15:51:53",
      "sourceId": 2,
      "resourceId": 12,
      "columnId": null,
      "title": "id",
      "column": "id",
      "type": "integer",
      "arrayType": null,
      "pathTitle": "test@id",
      "path": "$.id",
      "index": 0,
      "checked": 1
    }, {
      "id": 111,
      "updateTime": "2020-02-26 15:51:53",
      "sourceId": 2,
      "resourceId": 12,
      "columnId": null,
      "title": "width",
      "column": "width",
      "type": "integer",
      "arrayType": null,
      "pathTitle": "test@The Dimensions Schema@width",
      "path": "$.dimensions.width",
      "index": 0,
      "checked": 1
    }, {
      "id": 112,
      "updateTime": "2020-02-26 15:51:53",
      "sourceId": 2,
      "resourceId": 12,
      "columnId": null,
      "title": "height",
      "column": "height",
      "type": "integer",
      "arrayType": null,
      "pathTitle": "test@The Dimensions Schema@height",
      "path": "$.dimensions.height",
      "index": 0,
      "checked": 1
    }, {
      "id": 113,
      "updateTime": "2020-02-26 15:51:53",
      "sourceId": 2,
      "resourceId": 12,
      "columnId": null,
      "title": "dimensions",
      "column": null,
      "type": "object",
      "arrayType": null,
      "pathTitle": "test@The Dimensions Schema",
      "path": "$.dimensions",
      "index": 1,
      "checked": 1
    }, {
      "id": 114,
      "updateTime": "2020-02-26 15:51:53",
      "sourceId": 2,
      "resourceId": 12,
      "columnId": null,
      "title": "tags",
      "column": null,
      "type": "array",
      "arrayType": "object",
      "pathTitle": "test@The Tags Schema",
      "path": "$.tags[*]",
      "index": 1,
      "checked": 1
    }, {
      "id": 115,
      "updateTime": "2020-02-26 15:51:53",
      "sourceId": 2,
      "resourceId": 12,
      "columnId": null,
      "title": "name",
      "column": "name",
      "type": "string",
      "arrayType": null,
      "pathTitle": "test@The Tags Schema@name",
      "path": "$.tags[*].name",
      "index": 1,
      "checked": 1
    }, {
      "id": 116,
      "updateTime": "2020-02-26 15:51:53",
      "sourceId": 2,
      "resourceId": 12,
      "columnId": null,
      "title": "id",
      "column": "id",
      "type": "integer",
      "arrayType": null,
      "pathTitle": "test@The Tags Schema@id",
      "path": "$.tags[*].id",
      "index": 1,
      "checked": 1
    }]
  }, {
    "id": 13,
    "updateTime": "2020-02-26 15:51:53",
    "sourceId": 2,
    "title": "搜索",
    "path": "/serach/%E6%90%9C%E7%B4%A2",
    "method": null,
    "prefix": null,
    "value": "{\"definitions\":{},\"$schema\":\"http://json-schema.org/draft-07/schema#\",\"$id\":\"http://example.com/root.json\",\"type\":\"object\",\"title\":\"The Root Schema\",\"required\":[\"checked\",\"dimensions\",\"id\",\"name\",\"price\",\"tags\"],\"properties\":{\"checked\":{\"$id\":\"#/properties/checked\",\"type\":\"boolean\",\"title\":\"The Checked Schema\",\"default\":false,\"examples\":[false]},\"dimensions\":{\"$id\":\"#/properties/dimensions\",\"type\":\"object\",\"title\":\"The Dimensions Schema\",\"required\":[\"width\",\"height\"],\"properties\":{\"width\":{\"$id\":\"#/properties/dimensions/properties/width\",\"type\":\"integer\",\"title\":\"The Width Schema\",\"default\":0,\"examples\":[5]},\"height\":{\"$id\":\"#/properties/dimensions/properties/height\",\"type\":\"integer\",\"title\":\"The Height Schema\",\"default\":0,\"examples\":[10]}}},\"id\":{\"$id\":\"#/properties/id\",\"type\":\"integer\",\"title\":\"The Id Schema\",\"default\":0,\"examples\":[1]},\"name\":{\"$id\":\"#/properties/name\",\"type\":\"string\",\"title\":\"The Name Schema\",\"default\":\"\",\"examples\":[\"A green door\"],\"pattern\":\"^(.*)$\"},\"price\":{\"$id\":\"#/properties/price\",\"type\":\"number\",\"title\":\"The Price Schema\",\"default\":0.0,\"examples\":[12.5]},\"tags\":{\"$id\":\"#/properties/tags\",\"type\":\"array\",\"title\":\"The Tags Schema\",\"items\":{\"$id\":\"#/properties/tags/items\",\"type\":\"string\",\"title\":\"The Items Schema\",\"default\":\"\",\"examples\":[\"home\",\"green\"],\"pattern\":\"^(.*)$\"}}}}",
    "smColumns": [{
      "id": 117,
      "updateTime": "2020-02-26 15:51:53",
      "sourceId": 2,
      "resourceId": 13,
      "columnId": null,
      "title": "price",
      "column": "price",
      "type": "number",
      "arrayType": null,
      "pathTitle": "搜索@price",
      "path": "$.price",
      "index": 0,
      "checked": 1
    }, {
      "id": 118,
      "updateTime": "2020-02-26 15:51:53",
      "sourceId": 2,
      "resourceId": 13,
      "columnId": null,
      "title": "name",
      "column": "name",
      "type": "string",
      "arrayType": null,
      "pathTitle": "搜索@name",
      "path": "$.name",
      "index": 0,
      "checked": 1
    }, {
      "id": 119,
      "updateTime": "2020-02-26 15:51:53",
      "sourceId": 2,
      "resourceId": 13,
      "columnId": null,
      "title": "checked",
      "column": "checked",
      "type": "boolean",
      "arrayType": null,
      "pathTitle": "搜索@checked",
      "path": "$.checked",
      "index": 0,
      "checked": 1
    }, {
      "id": 120,
      "updateTime": "2020-02-26 15:51:53",
      "sourceId": 2,
      "resourceId": 13,
      "columnId": null,
      "title": "id",
      "column": "id",
      "type": "integer",
      "arrayType": null,
      "pathTitle": "搜索@id",
      "path": "$.id",
      "index": 0,
      "checked": 1
    }, {
      "id": 121,
      "updateTime": "2020-02-26 15:51:53",
      "sourceId": 2,
      "resourceId": 13,
      "columnId": null,
      "title": "width",
      "column": "width",
      "type": "integer",
      "arrayType": null,
      "pathTitle": "搜索@The Dimensions Schema@width",
      "path": "$.dimensions.width",
      "index": 0,
      "checked": 1
    }, {
      "id": 122,
      "updateTime": "2020-02-26 15:51:53",
      "sourceId": 2,
      "resourceId": 13,
      "columnId": null,
      "title": "height",
      "column": "height",
      "type": "integer",
      "arrayType": null,
      "pathTitle": "搜索@The Dimensions Schema@height",
      "path": "$.dimensions.height",
      "index": 0,
      "checked": 1
    }, {
      "id": 123,
      "updateTime": "2020-02-26 15:51:53",
      "sourceId": 2,
      "resourceId": 13,
      "columnId": null,
      "title": "dimensions",
      "column": null,
      "type": "object",
      "arrayType": null,
      "pathTitle": "搜索@The Dimensions Schema",
      "path": "$.dimensions",
      "index": 1,
      "checked": 1
    }, {
      "id": 124,
      "updateTime": "2020-02-26 15:51:53",
      "sourceId": 2,
      "resourceId": 13,
      "columnId": null,
      "title": "tags",
      "column": null,
      "type": "array",
      "arrayType": "string",
      "pathTitle": "搜索@The Tags Schema",
      "path": "$.tags[*]",
      "index": 1,
      "checked": 1
    }],
    "checkColumns": [{
      "id": 117,
      "updateTime": "2020-02-26 15:51:53",
      "sourceId": 2,
      "resourceId": 13,
      "columnId": null,
      "title": "price",
      "column": "price",
      "type": "number",
      "arrayType": null,
      "pathTitle": "搜索@price",
      "path": "$.price",
      "index": 0,
      "checked": 1
    }, {
      "id": 118,
      "updateTime": "2020-02-26 15:51:53",
      "sourceId": 2,
      "resourceId": 13,
      "columnId": null,
      "title": "name",
      "column": "name",
      "type": "string",
      "arrayType": null,
      "pathTitle": "搜索@name",
      "path": "$.name",
      "index": 0,
      "checked": 1
    }, {
      "id": 119,
      "updateTime": "2020-02-26 15:51:53",
      "sourceId": 2,
      "resourceId": 13,
      "columnId": null,
      "title": "checked",
      "column": "checked",
      "type": "boolean",
      "arrayType": null,
      "pathTitle": "搜索@checked",
      "path": "$.checked",
      "index": 0,
      "checked": 1
    }, {
      "id": 120,
      "updateTime": "2020-02-26 15:51:53",
      "sourceId": 2,
      "resourceId": 13,
      "columnId": null,
      "title": "id",
      "column": "id",
      "type": "integer",
      "arrayType": null,
      "pathTitle": "搜索@id",
      "path": "$.id",
      "index": 0,
      "checked": 1
    }, {
      "id": 121,
      "updateTime": "2020-02-26 15:51:53",
      "sourceId": 2,
      "resourceId": 13,
      "columnId": null,
      "title": "width",
      "column": "width",
      "type": "integer",
      "arrayType": null,
      "pathTitle": "搜索@The Dimensions Schema@width",
      "path": "$.dimensions.width",
      "index": 0,
      "checked": 1
    }, {
      "id": 122,
      "updateTime": "2020-02-26 15:51:53",
      "sourceId": 2,
      "resourceId": 13,
      "columnId": null,
      "title": "height",
      "column": "height",
      "type": "integer",
      "arrayType": null,
      "pathTitle": "搜索@The Dimensions Schema@height",
      "path": "$.dimensions.height",
      "index": 0,
      "checked": 1
    }, {
      "id": 123,
      "updateTime": "2020-02-26 15:51:53",
      "sourceId": 2,
      "resourceId": 13,
      "columnId": null,
      "title": "dimensions",
      "column": null,
      "type": "object",
      "arrayType": null,
      "pathTitle": "搜索@The Dimensions Schema",
      "path": "$.dimensions",
      "index": 1,
      "checked": 1
    }, {
      "id": 124,
      "updateTime": "2020-02-26 15:51:53",
      "sourceId": 2,
      "resourceId": 13,
      "columnId": null,
      "title": "tags",
      "column": null,
      "type": "array",
      "arrayType": "string",
      "pathTitle": "搜索@The Tags Schema",
      "path": "$.tags[*]",
      "index": 1,
      "checked": 1
    }]
  }, {
    "id": 1,
    "updateTime": "2020-02-26 15:51:50",
    "sourceId": 1,
    "title": "内容推送",
    "path": null,
    "method": null,
    "prefix": "修改前缀055",
    "value": "{\"definitions\":{},\"$schema\":\"http://json-schema.org/draft-07/schema#\",\"$id\":\"http://example.com/root.json\",\"type\":\"object\",\"title\":\"The Root Schema\",\"required\":[\"category\",\"categoryId\",\"content\",\"contentType\",\"status\",\"tag\",\"tagId\",\"title\"],\"properties\":{\"category\":{\"$id\":\"#/properties/category\",\"type\":\"string\",\"title\":\"The Category Schema\",\"default\":\"\",\"examples\":[\"分类062\"],\"pattern\":\"^(.*)$\"},\"categoryId\":{\"$id\":\"#/properties/categoryId\",\"type\":\"integer\",\"title\":\"The Categoryid Schema\",\"default\":0,\"examples\":[6]},\"content\":{\"$id\":\"#/properties/content\",\"type\":\"string\",\"title\":\"The Content Schema\",\"default\":\"\",\"examples\":[\"国家卫健委高级别专家组成员\"],\"pattern\":\"^(.*)$\"},\"contentType\":{\"$id\":\"#/properties/contentType\",\"type\":\"string\",\"title\":\"The Contenttype Schema\",\"default\":\"\",\"examples\":[\"content\"],\"pattern\":\"^(.*)$\"},\"status\":{\"$id\":\"#/properties/status\",\"type\":\"string\",\"title\":\"The Status Schema\",\"default\":\"\",\"examples\":[\"draft\"],\"pattern\":\"^(.*)$\"},\"tag\":{\"$id\":\"#/properties/tag\",\"type\":\"string\",\"title\":\"The Tag Schema\",\"default\":\"\",\"examples\":[\"标签011\"],\"pattern\":\"^(.*)$\"},\"tagId\":{\"$id\":\"#/properties/tagId\",\"type\":\"integer\",\"title\":\"The Tagid Schema\",\"default\":0,\"examples\":[9]},\"title\":{\"$id\":\"#/properties/title\",\"type\":\"string\",\"title\":\"The Title Schema\",\"default\":\"\",\"examples\":[\"推送标题080\"],\"pattern\":\"^(.*)$\"}}}",
    "smColumns": [{
      "id": 1,
      "updateTime": "2020-02-26 15:51:50",
      "sourceId": 1,
      "resourceId": 1,
      "columnId": null,
      "title": "tagId",
      "column": "tagId",
      "type": "integer",
      "arrayType": null,
      "pathTitle": "修改前缀055@tagId",
      "path": "$.tagId",
      "index": 0,
      "checked": 1
    }, {
      "id": 2,
      "updateTime": "2020-02-26 15:51:50",
      "sourceId": 1,
      "resourceId": 1,
      "columnId": null,
      "title": "tag",
      "column": "tag",
      "type": "string",
      "arrayType": null,
      "pathTitle": "修改前缀055@tag",
      "path": "$.tag",
      "index": 0,
      "checked": 1
    }, {
      "id": 3,
      "updateTime": "2020-02-26 15:51:50",
      "sourceId": 1,
      "resourceId": 1,
      "columnId": null,
      "title": "category",
      "column": "category",
      "type": "string",
      "arrayType": null,
      "pathTitle": "修改前缀055@category",
      "path": "$.category",
      "index": 0,
      "checked": 1
    }, {
      "id": 4,
      "updateTime": "2020-02-26 15:51:50",
      "sourceId": 1,
      "resourceId": 1,
      "columnId": null,
      "title": "title",
      "column": "title",
      "type": "string",
      "arrayType": null,
      "pathTitle": "修改前缀055@title",
      "path": "$.title",
      "index": 0,
      "checked": 1
    }, {
      "id": 5,
      "updateTime": "2020-02-26 15:51:50",
      "sourceId": 1,
      "resourceId": 1,
      "columnId": null,
      "title": "contentType",
      "column": "contentType",
      "type": "string",
      "arrayType": null,
      "pathTitle": "修改前缀055@contentType",
      "path": "$.contentType",
      "index": 0,
      "checked": 1
    }, {
      "id": 6,
      "updateTime": "2020-02-26 15:51:50",
      "sourceId": 1,
      "resourceId": 1,
      "columnId": null,
      "title": "categoryId",
      "column": "categoryId",
      "type": "integer",
      "arrayType": null,
      "pathTitle": "修改前缀055@categoryId",
      "path": "$.categoryId",
      "index": 0,
      "checked": 1
    }, {
      "id": 7,
      "updateTime": "2020-02-26 15:51:50",
      "sourceId": 1,
      "resourceId": 1,
      "columnId": null,
      "title": "content",
      "column": "content",
      "type": "string",
      "arrayType": null,
      "pathTitle": "修改前缀055@content",
      "path": "$.content",
      "index": 0,
      "checked": 1
    }, {
      "id": 8,
      "updateTime": "2020-02-26 15:51:50",
      "sourceId": 1,
      "resourceId": 1,
      "columnId": null,
      "title": "status",
      "column": "status",
      "type": "string",
      "arrayType": null,
      "pathTitle": "修改前缀055@status",
      "path": "$.status",
      "index": 0,
      "checked": 1
    }],
    "checkColumns": [{
      "id": 1,
      "updateTime": "2020-02-26 15:51:50",
      "sourceId": 1,
      "resourceId": 1,
      "columnId": null,
      "title": "tagId",
      "column": "tagId",
      "type": "integer",
      "arrayType": null,
      "pathTitle": "修改前缀055@tagId",
      "path": "$.tagId",
      "index": 0,
      "checked": 1
    }, {
      "id": 2,
      "updateTime": "2020-02-26 15:51:50",
      "sourceId": 1,
      "resourceId": 1,
      "columnId": null,
      "title": "tag",
      "column": "tag",
      "type": "string",
      "arrayType": null,
      "pathTitle": "修改前缀055@tag",
      "path": "$.tag",
      "index": 0,
      "checked": 1
    }, {
      "id": 3,
      "updateTime": "2020-02-26 15:51:50",
      "sourceId": 1,
      "resourceId": 1,
      "columnId": null,
      "title": "category",
      "column": "category",
      "type": "string",
      "arrayType": null,
      "pathTitle": "修改前缀055@category",
      "path": "$.category",
      "index": 0,
      "checked": 1
    }, {
      "id": 4,
      "updateTime": "2020-02-26 15:51:50",
      "sourceId": 1,
      "resourceId": 1,
      "columnId": null,
      "title": "title",
      "column": "title",
      "type": "string",
      "arrayType": null,
      "pathTitle": "修改前缀055@title",
      "path": "$.title",
      "index": 0,
      "checked": 1
    }, {
      "id": 5,
      "updateTime": "2020-02-26 15:51:50",
      "sourceId": 1,
      "resourceId": 1,
      "columnId": null,
      "title": "contentType",
      "column": "contentType",
      "type": "string",
      "arrayType": null,
      "pathTitle": "修改前缀055@contentType",
      "path": "$.contentType",
      "index": 0,
      "checked": 1
    }, {
      "id": 6,
      "updateTime": "2020-02-26 15:51:50",
      "sourceId": 1,
      "resourceId": 1,
      "columnId": null,
      "title": "categoryId",
      "column": "categoryId",
      "type": "integer",
      "arrayType": null,
      "pathTitle": "修改前缀055@categoryId",
      "path": "$.categoryId",
      "index": 0,
      "checked": 1
    }, {
      "id": 7,
      "updateTime": "2020-02-26 15:51:50",
      "sourceId": 1,
      "resourceId": 1,
      "columnId": null,
      "title": "content",
      "column": "content",
      "type": "string",
      "arrayType": null,
      "pathTitle": "修改前缀055@content",
      "path": "$.content",
      "index": 0,
      "checked": 1
    }, {
      "id": 8,
      "updateTime": "2020-02-26 15:51:50",
      "sourceId": 1,
      "resourceId": 1,
      "columnId": null,
      "title": "status",
      "column": "status",
      "type": "string",
      "arrayType": null,
      "pathTitle": "修改前缀055@status",
      "path": "$.status",
      "index": 0,
      "checked": 1
    }],
    "resourceId": 1,
    "resourceTitle": "内容推送"
  }],
  "title": "****",
  "tables": [{
    "id": 1,
    "updateTime": "2020-02-26 15:51:50",
    "sourceId": 1,
    "title": "内容推送",
    "path": null,
    "method": null,
    "prefix": "修改前缀055",
    "value": "{\"definitions\":{},\"$schema\":\"http://json-schema.org/draft-07/schema#\",\"$id\":\"http://example.com/root.json\",\"type\":\"object\",\"title\":\"The Root Schema\",\"required\":[\"category\",\"categoryId\",\"content\",\"contentType\",\"status\",\"tag\",\"tagId\",\"title\"],\"properties\":{\"category\":{\"$id\":\"#/properties/category\",\"type\":\"string\",\"title\":\"The Category Schema\",\"default\":\"\",\"examples\":[\"分类062\"],\"pattern\":\"^(.*)$\"},\"categoryId\":{\"$id\":\"#/properties/categoryId\",\"type\":\"integer\",\"title\":\"The Categoryid Schema\",\"default\":0,\"examples\":[6]},\"content\":{\"$id\":\"#/properties/content\",\"type\":\"string\",\"title\":\"The Content Schema\",\"default\":\"\",\"examples\":[\"国家卫健委高级别专家组成员\"],\"pattern\":\"^(.*)$\"},\"contentType\":{\"$id\":\"#/properties/contentType\",\"type\":\"string\",\"title\":\"The Contenttype Schema\",\"default\":\"\",\"examples\":[\"content\"],\"pattern\":\"^(.*)$\"},\"status\":{\"$id\":\"#/properties/status\",\"type\":\"string\",\"title\":\"The Status Schema\",\"default\":\"\",\"examples\":[\"draft\"],\"pattern\":\"^(.*)$\"},\"tag\":{\"$id\":\"#/properties/tag\",\"type\":\"string\",\"title\":\"The Tag Schema\",\"default\":\"\",\"examples\":[\"标签011\"],\"pattern\":\"^(.*)$\"},\"tagId\":{\"$id\":\"#/properties/tagId\",\"type\":\"integer\",\"title\":\"The Tagid Schema\",\"default\":0,\"examples\":[9]},\"title\":{\"$id\":\"#/properties/title\",\"type\":\"string\",\"title\":\"The Title Schema\",\"default\":\"\",\"examples\":[\"推送标题080\"],\"pattern\":\"^(.*)$\"}}}",
    "smColumns": [{
      "id": 1,
      "updateTime": "2020-02-26 15:51:50",
      "sourceId": 1,
      "resourceId": 1,
      "columnId": null,
      "title": "tagId",
      "column": "tagId",
      "type": "integer",
      "arrayType": null,
      "pathTitle": "修改前缀055@tagId",
      "path": "$.tagId",
      "index": 0,
      "checked": 1
    }, {
      "id": 2,
      "updateTime": "2020-02-26 15:51:50",
      "sourceId": 1,
      "resourceId": 1,
      "columnId": null,
      "title": "tag",
      "column": "tag",
      "type": "string",
      "arrayType": null,
      "pathTitle": "修改前缀055@tag",
      "path": "$.tag",
      "index": 0,
      "checked": 1
    }, {
      "id": 3,
      "updateTime": "2020-02-26 15:51:50",
      "sourceId": 1,
      "resourceId": 1,
      "columnId": null,
      "title": "category",
      "column": "category",
      "type": "string",
      "arrayType": null,
      "pathTitle": "修改前缀055@category",
      "path": "$.category",
      "index": 0,
      "checked": 1
    }, {
      "id": 4,
      "updateTime": "2020-02-26 15:51:50",
      "sourceId": 1,
      "resourceId": 1,
      "columnId": null,
      "title": "title",
      "column": "title",
      "type": "string",
      "arrayType": null,
      "pathTitle": "修改前缀055@title",
      "path": "$.title",
      "index": 0,
      "checked": 1
    }, {
      "id": 5,
      "updateTime": "2020-02-26 15:51:50",
      "sourceId": 1,
      "resourceId": 1,
      "columnId": null,
      "title": "contentType",
      "column": "contentType",
      "type": "string",
      "arrayType": null,
      "pathTitle": "修改前缀055@contentType",
      "path": "$.contentType",
      "index": 0,
      "checked": 1
    }, {
      "id": 6,
      "updateTime": "2020-02-26 15:51:50",
      "sourceId": 1,
      "resourceId": 1,
      "columnId": null,
      "title": "categoryId",
      "column": "categoryId",
      "type": "integer",
      "arrayType": null,
      "pathTitle": "修改前缀055@categoryId",
      "path": "$.categoryId",
      "index": 0,
      "checked": 1
    }, {
      "id": 7,
      "updateTime": "2020-02-26 15:51:50",
      "sourceId": 1,
      "resourceId": 1,
      "columnId": null,
      "title": "content",
      "column": "content",
      "type": "string",
      "arrayType": null,
      "pathTitle": "修改前缀055@content",
      "path": "$.content",
      "index": 0,
      "checked": 1
    }, {
      "id": 8,
      "updateTime": "2020-02-26 15:51:50",
      "sourceId": 1,
      "resourceId": 1,
      "columnId": null,
      "title": "status",
      "column": "status",
      "type": "string",
      "arrayType": null,
      "pathTitle": "修改前缀055@status",
      "path": "$.status",
      "index": 0,
      "checked": 1
    }],
    "checkColumns": [{
      "id": 1,
      "updateTime": "2020-02-26 15:51:50",
      "sourceId": 1,
      "resourceId": 1,
      "columnId": null,
      "title": "tagId",
      "column": "tagId",
      "type": "integer",
      "arrayType": null,
      "pathTitle": "修改前缀055@tagId",
      "path": "$.tagId",
      "index": 0,
      "checked": 1
    }, {
      "id": 2,
      "updateTime": "2020-02-26 15:51:50",
      "sourceId": 1,
      "resourceId": 1,
      "columnId": null,
      "title": "tag",
      "column": "tag",
      "type": "string",
      "arrayType": null,
      "pathTitle": "修改前缀055@tag",
      "path": "$.tag",
      "index": 0,
      "checked": 1
    }, {
      "id": 3,
      "updateTime": "2020-02-26 15:51:50",
      "sourceId": 1,
      "resourceId": 1,
      "columnId": null,
      "title": "category",
      "column": "category",
      "type": "string",
      "arrayType": null,
      "pathTitle": "修改前缀055@category",
      "path": "$.category",
      "index": 0,
      "checked": 1
    }, {
      "id": 4,
      "updateTime": "2020-02-26 15:51:50",
      "sourceId": 1,
      "resourceId": 1,
      "columnId": null,
      "title": "title",
      "column": "title",
      "type": "string",
      "arrayType": null,
      "pathTitle": "修改前缀055@title",
      "path": "$.title",
      "index": 0,
      "checked": 1
    }, {
      "id": 5,
      "updateTime": "2020-02-26 15:51:50",
      "sourceId": 1,
      "resourceId": 1,
      "columnId": null,
      "title": "contentType",
      "column": "contentType",
      "type": "string",
      "arrayType": null,
      "pathTitle": "修改前缀055@contentType",
      "path": "$.contentType",
      "index": 0,
      "checked": 1
    }, {
      "id": 6,
      "updateTime": "2020-02-26 15:51:50",
      "sourceId": 1,
      "resourceId": 1,
      "columnId": null,
      "title": "categoryId",
      "column": "categoryId",
      "type": "integer",
      "arrayType": null,
      "pathTitle": "修改前缀055@categoryId",
      "path": "$.categoryId",
      "index": 0,
      "checked": 1
    }, {
      "id": 7,
      "updateTime": "2020-02-26 15:51:50",
      "sourceId": 1,
      "resourceId": 1,
      "columnId": null,
      "title": "content",
      "column": "content",
      "type": "string",
      "arrayType": null,
      "pathTitle": "修改前缀055@content",
      "path": "$.content",
      "index": 0,
      "checked": 1
    }, {
      "id": 8,
      "updateTime": "2020-02-26 15:51:50",
      "sourceId": 1,
      "resourceId": 1,
      "columnId": null,
      "title": "status",
      "column": "status",
      "type": "string",
      "arrayType": null,
      "pathTitle": "修改前缀055@status",
      "path": "$.status",
      "index": 0,
      "checked": 1
    }],
    "resourceId": 1,
    "resourceTitle": "内容推送"
  }],
  "transferStatus": [],
  "rules": [{
    "item1": {
      "value": "223",
      "tableKey": "",
      "tableName": 3
    },
    "item2": {
      "value": "",
      "tableKey": "",
      "tableName": 99
    },
    "item3": {
      "value": "",
      "tableKey": "",
      "tableName": ""
    },
    "operation1": "==",
    "operation2": "=="
  }],
  "resourceId": 1,
  "mainTable": {
    "id": 1,
    "updateTime": "2020-02-26 15:51:50",
    "sourceId": 1,
    "title": "内容推送",
    "path": null,
    "method": null,
    "prefix": "修改前缀055",
    "value": "{\"definitions\":{},\"$schema\":\"http://json-schema.org/draft-07/schema#\",\"$id\":\"http://example.com/root.json\",\"type\":\"object\",\"title\":\"The Root Schema\",\"required\":[\"category\",\"categoryId\",\"content\",\"contentType\",\"status\",\"tag\",\"tagId\",\"title\"],\"properties\":{\"category\":{\"$id\":\"#/properties/category\",\"type\":\"string\",\"title\":\"The Category Schema\",\"default\":\"\",\"examples\":[\"分类062\"],\"pattern\":\"^(.*)$\"},\"categoryId\":{\"$id\":\"#/properties/categoryId\",\"type\":\"integer\",\"title\":\"The Categoryid Schema\",\"default\":0,\"examples\":[6]},\"content\":{\"$id\":\"#/properties/content\",\"type\":\"string\",\"title\":\"The Content Schema\",\"default\":\"\",\"examples\":[\"国家卫健委高级别专家组成员\"],\"pattern\":\"^(.*)$\"},\"contentType\":{\"$id\":\"#/properties/contentType\",\"type\":\"string\",\"title\":\"The Contenttype Schema\",\"default\":\"\",\"examples\":[\"content\"],\"pattern\":\"^(.*)$\"},\"status\":{\"$id\":\"#/properties/status\",\"type\":\"string\",\"title\":\"The Status Schema\",\"default\":\"\",\"examples\":[\"draft\"],\"pattern\":\"^(.*)$\"},\"tag\":{\"$id\":\"#/properties/tag\",\"type\":\"string\",\"title\":\"The Tag Schema\",\"default\":\"\",\"examples\":[\"标签011\"],\"pattern\":\"^(.*)$\"},\"tagId\":{\"$id\":\"#/properties/tagId\",\"type\":\"integer\",\"title\":\"The Tagid Schema\",\"default\":0,\"examples\":[9]},\"title\":{\"$id\":\"#/properties/title\",\"type\":\"string\",\"title\":\"The Title Schema\",\"default\":\"\",\"examples\":[\"推送标题080\"],\"pattern\":\"^(.*)$\"}}}",
    "smColumns": [{
      "id": 1,
      "updateTime": "2020-02-26 15:51:50",
      "sourceId": 1,
      "resourceId": 1,
      "columnId": null,
      "title": "tagId",
      "column": "tagId",
      "type": "integer",
      "arrayType": null,
      "pathTitle": "修改前缀055@tagId",
      "path": "$.tagId",
      "index": 0,
      "checked": 1
    }, {
      "id": 2,
      "updateTime": "2020-02-26 15:51:50",
      "sourceId": 1,
      "resourceId": 1,
      "columnId": null,
      "title": "tag",
      "column": "tag",
      "type": "string",
      "arrayType": null,
      "pathTitle": "修改前缀055@tag",
      "path": "$.tag",
      "index": 0,
      "checked": 1
    }, {
      "id": 3,
      "updateTime": "2020-02-26 15:51:50",
      "sourceId": 1,
      "resourceId": 1,
      "columnId": null,
      "title": "category",
      "column": "category",
      "type": "string",
      "arrayType": null,
      "pathTitle": "修改前缀055@category",
      "path": "$.category",
      "index": 0,
      "checked": 1
    }, {
      "id": 4,
      "updateTime": "2020-02-26 15:51:50",
      "sourceId": 1,
      "resourceId": 1,
      "columnId": null,
      "title": "title",
      "column": "title",
      "type": "string",
      "arrayType": null,
      "pathTitle": "修改前缀055@title",
      "path": "$.title",
      "index": 0,
      "checked": 1
    }, {
      "id": 5,
      "updateTime": "2020-02-26 15:51:50",
      "sourceId": 1,
      "resourceId": 1,
      "columnId": null,
      "title": "contentType",
      "column": "contentType",
      "type": "string",
      "arrayType": null,
      "pathTitle": "修改前缀055@contentType",
      "path": "$.contentType",
      "index": 0,
      "checked": 1
    }, {
      "id": 6,
      "updateTime": "2020-02-26 15:51:50",
      "sourceId": 1,
      "resourceId": 1,
      "columnId": null,
      "title": "categoryId",
      "column": "categoryId",
      "type": "integer",
      "arrayType": null,
      "pathTitle": "修改前缀055@categoryId",
      "path": "$.categoryId",
      "index": 0,
      "checked": 1
    }, {
      "id": 7,
      "updateTime": "2020-02-26 15:51:50",
      "sourceId": 1,
      "resourceId": 1,
      "columnId": null,
      "title": "content",
      "column": "content",
      "type": "string",
      "arrayType": null,
      "pathTitle": "修改前缀055@content",
      "path": "$.content",
      "index": 0,
      "checked": 1
    }, {
      "id": 8,
      "updateTime": "2020-02-26 15:51:50",
      "sourceId": 1,
      "resourceId": 1,
      "columnId": null,
      "title": "status",
      "column": "status",
      "type": "string",
      "arrayType": null,
      "pathTitle": "修改前缀055@status",
      "path": "$.status",
      "index": 0,
      "checked": 1
    }],
    "checkColumns": [{
      "id": 1,
      "updateTime": "2020-02-26 15:51:50",
      "sourceId": 1,
      "resourceId": 1,
      "columnId": null,
      "title": "tagId",
      "column": "tagId",
      "type": "integer",
      "arrayType": null,
      "pathTitle": "修改前缀055@tagId",
      "path": "$.tagId",
      "index": 0,
      "checked": 1
    }, {
      "id": 2,
      "updateTime": "2020-02-26 15:51:50",
      "sourceId": 1,
      "resourceId": 1,
      "columnId": null,
      "title": "tag",
      "column": "tag",
      "type": "string",
      "arrayType": null,
      "pathTitle": "修改前缀055@tag",
      "path": "$.tag",
      "index": 0,
      "checked": 1
    }, {
      "id": 3,
      "updateTime": "2020-02-26 15:51:50",
      "sourceId": 1,
      "resourceId": 1,
      "columnId": null,
      "title": "category",
      "column": "category",
      "type": "string",
      "arrayType": null,
      "pathTitle": "修改前缀055@category",
      "path": "$.category",
      "index": 0,
      "checked": 1
    }, {
      "id": 4,
      "updateTime": "2020-02-26 15:51:50",
      "sourceId": 1,
      "resourceId": 1,
      "columnId": null,
      "title": "title",
      "column": "title",
      "type": "string",
      "arrayType": null,
      "pathTitle": "修改前缀055@title",
      "path": "$.title",
      "index": 0,
      "checked": 1
    }, {
      "id": 5,
      "updateTime": "2020-02-26 15:51:50",
      "sourceId": 1,
      "resourceId": 1,
      "columnId": null,
      "title": "contentType",
      "column": "contentType",
      "type": "string",
      "arrayType": null,
      "pathTitle": "修改前缀055@contentType",
      "path": "$.contentType",
      "index": 0,
      "checked": 1
    }, {
      "id": 6,
      "updateTime": "2020-02-26 15:51:50",
      "sourceId": 1,
      "resourceId": 1,
      "columnId": null,
      "title": "categoryId",
      "column": "categoryId",
      "type": "integer",
      "arrayType": null,
      "pathTitle": "修改前缀055@categoryId",
      "path": "$.categoryId",
      "index": 0,
      "checked": 1
    }, {
      "id": 7,
      "updateTime": "2020-02-26 15:51:50",
      "sourceId": 1,
      "resourceId": 1,
      "columnId": null,
      "title": "content",
      "column": "content",
      "type": "string",
      "arrayType": null,
      "pathTitle": "修改前缀055@content",
      "path": "$.content",
      "index": 0,
      "checked": 1
    }, {
      "id": 8,
      "updateTime": "2020-02-26 15:51:50",
      "sourceId": 1,
      "resourceId": 1,
      "columnId": null,
      "title": "status",
      "column": "status",
      "type": "string",
      "arrayType": null,
      "pathTitle": "修改前缀055@status",
      "path": "$.status",
      "index": 0,
      "checked": 1
    }],
    "resourceId": 1,
    "resourceTitle": "内容推送"
  },
  "tagId": 2,
  "mainResourceId": 1,
  "tag": "标签修改077",
  "resourceTitle": "内容推送",
  "status": "enabled"
}
